clickframes/__init__.py
clickframes/_version.py
clickframes/core.py
clickframes-0.1.0a1.dist-info/licenses/LICENSE
clickframes-0.1.0a1.dist-info/METADATA
clickframes-0.1.0a1.dist-info/WHEEL
clickframes-0.1.0a1.dist-info/top_level.txt
clickframes-0.1.0a1.dist-info/RECORD
